{".class":"MypyFile","_fullname":"paddle.autograd.autograd","future_import_flags":["annotations"],"is_partial_stub_package":false,"is_stub":false,"names":{".class":"SymbolTable","Hessian":{".class":"SymbolTableNode","kind":"Gdef","node":{".class":"TypeInfo","_promote":[],"abstract_attributes":[],"alt_promote":null,"bases":["paddle.autograd.autograd.Jacobian"],"dataclass_transform_spec":null,"declared_metaclass":null,"defn":{".class":"ClassDef","fullname":"paddle.autograd.autograd.Hessian","name":"Hessian","type_vars":[]},"deletable_attributes":[],"deprecated":null,"flags":[],"fullname":"paddle.autograd.autograd.Hessian","has_param_spec_type":false,"metaclass_type":null,"metadata":{},"module_name":"paddle.autograd.autograd","mro":["paddle.autograd.autograd.Hessian","paddle.autograd.autograd.Jacobian","builtins.object"],"names":{".class":"SymbolTable"},"self_type":{".class":"TypeVarType","default":{".class":"AnyType","missing_import_name":null,"source_any":null,"type_of_any":4},"fullname":"paddle.autograd.autograd.Hessian.Self","id":0,"name":"Self","namespace":"","upper_bound":"paddle.autograd.autograd.Hessian","values":[],"variance":0},"slots":null,"tuple_type":null,"type_vars":[],"typeddict_type":null}},"Jacobian":{".class":"SymbolTableNode","kind":"Gdef","node":{".class":"TypeInfo","_promote":[],"abstract_attributes":[],"alt_promote":null,"bases":["builtins.object"],"dataclass_transform_spec":null,"declared_metaclass":null,"defn":{".class":"ClassDef","fullname":"paddle.autograd.autograd.Jacobian","name":"Jacobian","type_vars":[]},"deletable_attributes":[],"deprecated":null,"flags":[],"fullname":"paddle.autograd.autograd.Jacobian","has_param_spec_type":false,"metaclass_type":null,"metadata":{},"module_name":"paddle.autograd.autograd","mro":["paddle.autograd.autograd.Jacobian","builtins.object"],"names":{".class":"SymbolTable","__add__":{".class":"SymbolTableNode","kind":"Mdef","node":{".class":"FuncDef","abstract_status":0,"arg_kinds":[0,0],"arg_names":[null,null],"dataclass_transform_spec":null,"deprecated":null,"flags":[],"fullname":"paddle.autograd.autograd.Jacobian.__add__","name":"__add__","type":null}},"__div__":{".class":"SymbolTableNode","kind":"Mdef","node":{".class":"FuncDef","abstract_status":0,"arg_kinds":[0,0],"arg_names":["self","other"],"dataclass_transform_spec":null,"deprecated":null,"flags":[],"fullname":"paddle.autograd.autograd.Jacobian.__div__","name":"__div__","type":null}},"__eq__":{".class":"SymbolTableNode","kind":"Mdef","node":{".class":"FuncDef","abstract_status":0,"arg_kinds":[0,0],"arg_names":[null,null],"dataclass_transform_spec":null,"deprecated":null,"flags":[],"fullname":"paddle.autograd.autograd.Jacobian.__eq__","name":"__eq__","type":null}},"__floordiv__":{".class":"SymbolTableNode","kind":"Mdef","node":{".class":"FuncDef","abstract_status":0,"arg_kinds":[0,0],"arg_names":[null,null],"dataclass_transform_spec":null,"deprecated":null,"flags":[],"fullname":"paddle.autograd.autograd.Jacobian.__floordiv__","name":"__floordiv__","type":null}},"__ge__":{".class":"SymbolTableNode","kind":"Mdef","node":{".class":"FuncDef","abstract_status":0,"arg_kinds":[0,0],"arg_names":[null,null],"dataclass_transform_spec":null,"deprecated":null,"flags":[],"fullname":"paddle.autograd.autograd.Jacobian.__ge__","name":"__ge__","type":null}},"__getattr__":{".class":"SymbolTableNode","kind":"Mdef","node":{".class":"FuncDef","abstract_status":0,"arg_kinds":[0,0],"arg_names":[null,null],"dataclass_transform_spec":null,"deprecated":null,"flags":[],"fullname":"paddle.autograd.autograd.Jacobian.__getattr__","name":"__getattr__","type":{".class":"CallableType","arg_kinds":[0,0],"arg_names":[null,null],"arg_types":["paddle.autograd.autograd.Jacobian","builtins.str"],"bound_args":[],"def_extras":{"first_arg":"self"},"fallback":"builtins.function","from_concatenate":false,"implicit":false,"imprecise_arg_kinds":false,"is_ellipsis_args":false,"name":"__getattr__ of Jacobian","ret_type":{".class":"AnyType","missing_import_name":null,"source_any":null,"type_of_any":1},"type_guard":null,"type_is":null,"unpack_kwargs":false,"variables":[]}}},"__getitem__":{".class":"SymbolTableNode","kind":"Mdef","node":{".class":"FuncDef","abstract_status":0,"arg_kinds":[0,0],"arg_names":[null,null],"dataclass_transform_spec":null,"deprecated":null,"flags":[],"fullname":"paddle.autograd.autograd.Jacobian.__getitem__","name":"__getitem__","type":null}},"__gt__":{".class":"SymbolTableNode","kind":"Mdef","node":{".class":"FuncDef","abstract_status":0,"arg_kinds":[0,0],"arg_names":[null,null],"dataclass_transform_spec":null,"deprecated":null,"flags":[],"fullname":"paddle.autograd.autograd.Jacobian.__gt__","name":"__gt__","type":null}},"__init__":{".class":"SymbolTableNode","kind":"Mdef","node":{".class":"FuncDef","abstract_status":0,"arg_kinds":[0,0,0,1],"arg_names":["self","ys","xs","is_batched"],"dataclass_transform_spec":null,"deprecated":null,"flags":[],"fullname":"paddle.autograd.autograd.Jacobian.__init__","name":"__init__","type":{".class":"CallableType","arg_kinds":[0,0,0,1],"arg_names":["self","ys","xs","is_batched"],"arg_types":["paddle.autograd.autograd.Jacobian","paddle.tensor.tensor.Tensor","paddle.tensor.tensor.Tensor","builtins.bool"],"bound_args":[],"def_extras":{"first_arg":"self"},"fallback":"builtins.function","from_concatenate":false,"implicit":false,"imprecise_arg_kinds":false,"is_ellipsis_args":false,"name":"__init__ of Jacobian","ret_type":{".class":"NoneType"},"type_guard":null,"type_is":null,"unpack_kwargs":false,"variables":[]}}},"__le__":{".class":"SymbolTableNode","kind":"Mdef","node":{".class":"FuncDef","abstract_status":0,"arg_kinds":[0,0],"arg_names":[null,null],"dataclass_transform_spec":null,"deprecated":null,"flags":[],"fullname":"paddle.autograd.autograd.Jacobian.__le__","name":"__le__","type":null}},"__lt__":{".class":"SymbolTableNode","kind":"Mdef","node":{".class":"FuncDef","abstract_status":0,"arg_kinds":[0,0],"arg_names":[null,null],"dataclass_transform_spec":null,"deprecated":null,"flags":[],"fullname":"paddle.autograd.autograd.Jacobian.__lt__","name":"__lt__","type":null}},"__matmul__":{".class":"SymbolTableNode","kind":"Mdef","node":{".class":"FuncDef","abstract_status":0,"arg_kinds":[0,0],"arg_names":[null,null],"dataclass_transform_spec":null,"deprecated":null,"flags":[],"fullname":"paddle.autograd.autograd.Jacobian.__matmul__","name":"__matmul__","type":null}},"__mod__":{".class":"SymbolTableNode","kind":"Mdef","node":{".class":"FuncDef","abstract_status":0,"arg_kinds":[0,0],"arg_names":[null,null],"dataclass_transform_spec":null,"deprecated":null,"flags":[],"fullname":"paddle.autograd.autograd.Jacobian.__mod__","name":"__mod__","type":null}},"__mul__":{".class":"SymbolTableNode","kind":"Mdef","node":{".class":"FuncDef","abstract_status":0,"arg_kinds":[0,0],"arg_names":[null,null],"dataclass_transform_spec":null,"deprecated":null,"flags":[],"fullname":"paddle.autograd.autograd.Jacobian.__mul__","name":"__mul__","type":null}},"__ne__":{".class":"SymbolTableNode","kind":"Mdef","node":{".class":"FuncDef","abstract_status":0,"arg_kinds":[0,0],"arg_names":[null,null],"dataclass_transform_spec":null,"deprecated":null,"flags":[],"fullname":"paddle.autograd.autograd.Jacobian.__ne__","name":"__ne__","type":null}},"__pow__":{".class":"SymbolTableNode","kind":"Mdef","node":{".class":"FuncDef","abstract_status":0,"arg_kinds":[0,0],"arg_names":[null,null],"dataclass_transform_spec":null,"deprecated":null,"flags":[],"fullname":"paddle.autograd.autograd.Jacobian.__pow__","name":"__pow__","type":null}},"__sub__":{".class":"SymbolTableNode","kind":"Mdef","node":{".class":"FuncDef","abstract_status":0,"arg_kinds":[0,0],"arg_names":[null,null],"dataclass_transform_spec":null,"deprecated":null,"flags":[],"fullname":"paddle.autograd.autograd.Jacobian.__sub__","name":"__sub__","type":null}},"__truediv__":{".class":"SymbolTableNode","kind":"Mdef","node":{".class":"FuncDef","abstract_status":0,"arg_kinds":[0,0],"arg_names":[null,null],"dataclass_transform_spec":null,"deprecated":null,"flags":[],"fullname":"paddle.autograd.autograd.Jacobian.__truediv__","name":"__truediv__","type":null}},"_jacobian":{".class":"SymbolTableNode","implicit":true,"kind":"Mdef","node":{".class":"Var","flags":["is_inferred"],"fullname":"paddle.autograd.autograd.Jacobian._jacobian","name":"_jacobian","type":"paddle.autograd.autograd._JacobianNoBatch"}},"shape":{".class":"SymbolTableNode","kind":"Mdef","node":{".class":"Decorator","func":{".class":"FuncDef","abstract_status":0,"arg_kinds":[0],"arg_names":["self"],"dataclass_transform_spec":null,"deprecated":null,"flags":["is_property","is_decorated"],"fullname":"paddle.autograd.autograd.Jacobian.shape","name":"shape","type":{".class":"CallableType","arg_kinds":[0],"arg_names":["self"],"arg_types":["paddle.autograd.autograd.Jacobian"],"bound_args":[],"def_extras":{"first_arg":"self"},"fallback":"builtins.function","from_concatenate":false,"implicit":false,"imprecise_arg_kinds":false,"is_ellipsis_args":false,"name":"shape of Jacobian","ret_type":{".class":"Instance","args":["builtins.int"],"extra_attrs":null,"type_ref":"builtins.list"},"type_guard":null,"type_is":null,"unpack_kwargs":false,"variables":[]}},"is_overload":false,"var":{".class":"Var","flags":["is_initialized_in_class","is_property","is_ready","is_inferred"],"fullname":"paddle.autograd.autograd.Jacobian.shape","name":"shape","type":{".class":"CallableType","arg_kinds":[0],"arg_names":["self"],"arg_types":["paddle.autograd.autograd.Jacobian"],"bound_args":[],"def_extras":{"first_arg":"self"},"fallback":"builtins.function","from_concatenate":false,"implicit":false,"imprecise_arg_kinds":false,"is_ellipsis_args":false,"name":"shape of Jacobian","ret_type":{".class":"Instance","args":["builtins.int"],"extra_attrs":null,"type_ref":"builtins.list"},"type_guard":null,"type_is":null,"unpack_kwargs":false,"variables":[]}}}}},"self_type":{".class":"TypeVarType","default":{".class":"AnyType","missing_import_name":null,"source_any":null,"type_of_any":4},"fullname":"paddle.autograd.autograd.Jacobian.Self","id":0,"name":"Self","namespace":"","upper_bound":"paddle.autograd.autograd.Jacobian","values":[],"variance":0},"slots":null,"tuple_type":null,"type_vars":[],"typeddict_type":null}},"Sequence":{".class":"SymbolTableNode","cross_ref":"typing.Sequence","kind":"Gdef","module_hidden":true,"module_public":false},"TYPE_CHECKING":{".class":"SymbolTableNode","cross_ref":"typing.TYPE_CHECKING","kind":"Gdef","module_hidden":true,"module_public":false},"Tensor":{".class":"SymbolTableNode","cross_ref":"paddle.tensor.tensor.Tensor","kind":"Gdef","module_hidden":true,"module_public":false},"_Jacobian":{".class":"SymbolTableNode","kind":"Gdef","node":{".class":"TypeInfo","_promote":[],"abstract_attributes":[],"alt_promote":null,"bases":["builtins.object"],"dataclass_transform_spec":null,"declared_metaclass":null,"defn":{".class":"ClassDef","fullname":"paddle.autograd.autograd._Jacobian","name":"_Jacobian","type_vars":[]},"deletable_attributes":[],"deprecated":null,"flags":[],"fullname":"paddle.autograd.autograd._Jacobian","has_param_spec_type":false,"metaclass_type":null,"metadata":{},"module_name":"paddle.autograd.autograd","mro":["paddle.autograd.autograd._Jacobian","builtins.object"],"names":{".class":"SymbolTable","__getitem__":{".class":"SymbolTableNode","kind":"Mdef","node":{".class":"FuncDef","abstract_status":0,"arg_kinds":[0,0],"arg_names":[null,null],"dataclass_transform_spec":null,"deprecated":null,"flags":[],"fullname":"paddle.autograd.autograd._Jacobian.__getitem__","name":"__getitem__","type":null}},"__init__":{".class":"SymbolTableNode","kind":"Mdef","node":{".class":"FuncDef","abstract_status":0,"arg_kinds":[0,0,0],"arg_names":["self","ys","xs"],"dataclass_transform_spec":null,"deprecated":null,"flags":[],"fullname":"paddle.autograd.autograd._Jacobian.__init__","name":"__init__","type":null}},"_cache":{".class":"SymbolTableNode","implicit":true,"kind":"Mdef","node":{".class":"Var","flags":["is_inferred","invalid_partial_type"],"fullname":"paddle.autograd.autograd._Jacobian._cache","name":"_cache","type":{".class":"Instance","args":[{".class":"AnyType","missing_import_name":null,"source_any":null,"type_of_any":1},{".class":"AnyType","missing_import_name":null,"source_any":null,"type_of_any":1}],"extra_attrs":null,"type_ref":"builtins.dict"}}},"_cached_evaluate":{".class":"SymbolTableNode","kind":"Mdef","node":{".class":"FuncDef","abstract_status":0,"arg_kinds":[0,0],"arg_names":["self","k"],"dataclass_transform_spec":null,"deprecated":null,"flags":[],"fullname":"paddle.autograd.autograd._Jacobian._cached_evaluate","name":"_cached_evaluate","type":null}},"_evaluate":{".class":"SymbolTableNode","kind":"Mdef","node":{".class":"FuncDef","abstract_status":0,"arg_kinds":[0,0],"arg_names":["self","index"],"dataclass_transform_spec":null,"deprecated":null,"flags":[],"fullname":"paddle.autograd.autograd._Jacobian._evaluate","name":"_evaluate","type":null}},"_evaluate_all":{".class":"SymbolTableNode","kind":"Mdef","node":{".class":"FuncDef","abstract_status":0,"arg_kinds":[0],"arg_names":["self"],"dataclass_transform_spec":null,"deprecated":null,"flags":[],"fullname":"paddle.autograd.autograd._Jacobian._evaluate_all","name":"_evaluate_all","type":null}},"_flatten":{".class":"SymbolTableNode","kind":"Mdef","node":{".class":"FuncDef","abstract_status":0,"arg_kinds":[0,0],"arg_names":["self","xs"],"dataclass_transform_spec":null,"deprecated":null,"flags":[],"fullname":"paddle.autograd.autograd._Jacobian._flatten","name":"_flatten","type":null}},"_flatten_xs":{".class":"SymbolTableNode","implicit":true,"kind":"Mdef","node":{".class":"Var","flags":["is_inferred"],"fullname":"paddle.autograd.autograd._Jacobian._flatten_xs","name":"_flatten_xs","type":{".class":"AnyType","missing_import_name":null,"source_any":null,"type_of_any":1}}},"_flatten_ys":{".class":"SymbolTableNode","implicit":true,"kind":"Mdef","node":{".class":"Var","flags":["is_inferred"],"fullname":"paddle.autograd.autograd._Jacobian._flatten_ys","name":"_flatten_ys","type":{".class":"AnyType","missing_import_name":null,"source_any":null,"type_of_any":1}}},"_lazy_axis":{".class":"SymbolTableNode","kind":"Mdef","node":{".class":"Decorator","func":{".class":"FuncDef","abstract_status":0,"arg_kinds":[0],"arg_names":["self"],"dataclass_transform_spec":null,"deprecated":null,"flags":["is_property","is_decorated"],"fullname":"paddle.autograd.autograd._Jacobian._lazy_axis","name":"_lazy_axis","type":null},"is_overload":false,"var":{".class":"Var","flags":["is_initialized_in_class","is_property","is_ready","is_inferred"],"fullname":"paddle.autograd.autograd._Jacobian._lazy_axis","name":"_lazy_axis","type":{".class":"CallableType","arg_kinds":[0],"arg_names":["self"],"arg_types":["paddle.autograd.autograd._Jacobian"],"bound_args":[],"def_extras":{"first_arg":"self"},"fallback":"builtins.function","from_concatenate":false,"implicit":true,"imprecise_arg_kinds":false,"is_ellipsis_args":false,"name":"_lazy_axis of _Jacobian","ret_type":{".class":"AnyType","missing_import_name":null,"source_any":null,"type_of_any":1},"type_guard":null,"type_is":null,"unpack_kwargs":false,"variables":[]}}}},"_lazy_indexes":{".class":"SymbolTableNode","kind":"Mdef","node":{".class":"FuncDef","abstract_status":0,"arg_kinds":[0,0],"arg_names":["self","indexes"],"dataclass_transform_spec":null,"deprecated":null,"flags":[],"fullname":"paddle.autograd.autograd._Jacobian._lazy_indexes","name":"_lazy_indexes","type":null}},"_shifted_indexes":{".class":"SymbolTableNode","kind":"Mdef","node":{".class":"FuncDef","abstract_status":0,"arg_kinds":[0,0,1],"arg_names":["self","indexes","lazy_axis_size"],"dataclass_transform_spec":null,"deprecated":null,"flags":[],"fullname":"paddle.autograd.autograd._Jacobian._shifted_indexes","name":"_shifted_indexes","type":null}},"_xs":{".class":"SymbolTableNode","implicit":true,"kind":"Mdef","node":{".class":"Var","flags":["is_inferred"],"fullname":"paddle.autograd.autograd._Jacobian._xs","name":"_xs","type":{".class":"AnyType","missing_import_name":null,"source_any":null,"type_of_any":1}}},"_ys":{".class":"SymbolTableNode","implicit":true,"kind":"Mdef","node":{".class":"Var","flags":["is_inferred"],"fullname":"paddle.autograd.autograd._Jacobian._ys","name":"_ys","type":{".class":"AnyType","missing_import_name":null,"source_any":null,"type_of_any":1}}},"original_xs_shape":{".class":"SymbolTableNode","implicit":true,"kind":"Mdef","node":{".class":"Var","flags":["is_inferred"],"fullname":"paddle.autograd.autograd._Jacobian.original_xs_shape","name":"original_xs_shape","type":{".class":"AnyType","missing_import_name":null,"source_any":{".class":"AnyType","missing_import_name":null,"source_any":null,"type_of_any":1},"type_of_any":7}}},"original_ys_shape":{".class":"SymbolTableNode","implicit":true,"kind":"Mdef","node":{".class":"Var","flags":["is_inferred"],"fullname":"paddle.autograd.autograd._Jacobian.original_ys_shape","name":"original_ys_shape","type":{".class":"AnyType","missing_import_name":null,"source_any":{".class":"AnyType","missing_import_name":null,"source_any":null,"type_of_any":1},"type_of_any":7}}}},"self_type":{".class":"TypeVarType","default":{".class":"AnyType","missing_import_name":null,"source_any":null,"type_of_any":4},"fullname":"paddle.autograd.autograd._Jacobian.Self","id":0,"name":"Self","namespace":"","upper_bound":"paddle.autograd.autograd._Jacobian","values":[],"variance":0},"slots":null,"tuple_type":null,"type_vars":[],"typeddict_type":null}},"_JacobianBatchFirst":{".class":"SymbolTableNode","kind":"Gdef","node":{".class":"TypeInfo","_promote":[],"abstract_attributes":[],"alt_promote":null,"bases":["paddle.autograd.autograd._Jacobian"],"dataclass_transform_spec":null,"declared_metaclass":null,"defn":{".class":"ClassDef","fullname":"paddle.autograd.autograd._JacobianBatchFirst","name":"_JacobianBatchFirst","type_vars":[]},"deletable_attributes":[],"deprecated":null,"flags":[],"fullname":"paddle.autograd.autograd._JacobianBatchFirst","has_param_spec_type":false,"metaclass_type":null,"metadata":{},"module_name":"paddle.autograd.autograd","mro":["paddle.autograd.autograd._JacobianBatchFirst","paddle.autograd.autograd._Jacobian","builtins.object"],"names":{".class":"SymbolTable","__init__":{".class":"SymbolTableNode","kind":"Mdef","node":{".class":"FuncDef","abstract_status":0,"arg_kinds":[0,0,0],"arg_names":["self","ys","xs"],"dataclass_transform_spec":null,"deprecated":null,"flags":[],"fullname":"paddle.autograd.autograd._JacobianBatchFirst.__init__","name":"__init__","type":null}},"_evaluate":{".class":"SymbolTableNode","kind":"Mdef","node":{".class":"FuncDef","abstract_status":0,"arg_kinds":[0,0],"arg_names":["self","row_index"],"dataclass_transform_spec":null,"deprecated":null,"flags":[],"fullname":"paddle.autograd.autograd._JacobianBatchFirst._evaluate","name":"_evaluate","type":null}},"_flatten":{".class":"SymbolTableNode","kind":"Mdef","node":{".class":"FuncDef","abstract_status":0,"arg_kinds":[0,0],"arg_names":["self","xs"],"dataclass_transform_spec":null,"deprecated":null,"flags":[],"fullname":"paddle.autograd.autograd._JacobianBatchFirst._flatten","name":"_flatten","type":null}},"_lazy_axis":{".class":"SymbolTableNode","kind":"Mdef","node":{".class":"Decorator","func":{".class":"FuncDef","abstract_status":0,"arg_kinds":[0],"arg_names":["self"],"dataclass_transform_spec":null,"deprecated":null,"flags":["is_property","is_decorated"],"fullname":"paddle.autograd.autograd._JacobianBatchFirst._lazy_axis","name":"_lazy_axis","type":null},"is_overload":false,"var":{".class":"Var","flags":["is_initialized_in_class","is_property","is_ready","is_inferred"],"fullname":"paddle.autograd.autograd._JacobianBatchFirst._lazy_axis","name":"_lazy_axis","type":{".class":"CallableType","arg_kinds":[0],"arg_names":["self"],"arg_types":["paddle.autograd.autograd._JacobianBatchFirst"],"bound_args":[],"def_extras":{"first_arg":"self"},"fallback":"builtins.function","from_concatenate":false,"implicit":true,"imprecise_arg_kinds":false,"is_ellipsis_args":false,"name":"_lazy_axis of _JacobianBatchFirst","ret_type":{".class":"AnyType","missing_import_name":null,"source_any":null,"type_of_any":1},"type_guard":null,"type_is":null,"unpack_kwargs":false,"variables":[]}}}},"inner_shape":{".class":"SymbolTableNode","implicit":true,"kind":"Mdef","node":{".class":"Var","flags":["is_inferred"],"fullname":"paddle.autograd.autograd._JacobianBatchFirst.inner_shape","name":"inner_shape","type":{".class":"Instance","args":[{".class":"AnyType","missing_import_name":null,"source_any":{".class":"AnyType","missing_import_name":null,"source_any":null,"type_of_any":5},"type_of_any":7}],"extra_attrs":null,"type_ref":"builtins.list"}}},"is_batched":{".class":"SymbolTableNode","implicit":true,"kind":"Mdef","node":{".class":"Var","flags":["is_inferred"],"fullname":"paddle.autograd.autograd._JacobianBatchFirst.is_batched","name":"is_batched","type":"builtins.bool"}},"shape":{".class":"SymbolTableNode","implicit":true,"kind":"Mdef","node":{".class":"Var","flags":["is_inferred"],"fullname":"paddle.autograd.autograd._JacobianBatchFirst.shape","name":"shape","type":{".class":"Instance","args":[{".class":"AnyType","missing_import_name":null,"source_any":{".class":"AnyType","missing_import_name":null,"source_any":null,"type_of_any":5},"type_of_any":7}],"extra_attrs":null,"type_ref":"builtins.list"}}}},"self_type":{".class":"TypeVarType","default":{".class":"AnyType","missing_import_name":null,"source_any":null,"type_of_any":4},"fullname":"paddle.autograd.autograd._JacobianBatchFirst.Self","id":0,"name":"Self","namespace":"","upper_bound":"paddle.autograd.autograd._JacobianBatchFirst","values":[],"variance":0},"slots":null,"tuple_type":null,"type_vars":[],"typeddict_type":null}},"_JacobianNoBatch":{".class":"SymbolTableNode","kind":"Gdef","node":{".class":"TypeInfo","_promote":[],"abstract_attributes":[],"alt_promote":null,"bases":["paddle.autograd.autograd._Jacobian"],"dataclass_transform_spec":null,"declared_metaclass":null,"defn":{".class":"ClassDef","fullname":"paddle.autograd.autograd._JacobianNoBatch","name":"_JacobianNoBatch","type_vars":[]},"deletable_attributes":[],"deprecated":null,"flags":[],"fullname":"paddle.autograd.autograd._JacobianNoBatch","has_param_spec_type":false,"metaclass_type":null,"metadata":{},"module_name":"paddle.autograd.autograd","mro":["paddle.autograd.autograd._JacobianNoBatch","paddle.autograd.autograd._Jacobian","builtins.object"],"names":{".class":"SymbolTable","__init__":{".class":"SymbolTableNode","kind":"Mdef","node":{".class":"FuncDef","abstract_status":0,"arg_kinds":[0,0,0],"arg_names":["self","ys","xs"],"dataclass_transform_spec":null,"deprecated":null,"flags":[],"fullname":"paddle.autograd.autograd._JacobianNoBatch.__init__","name":"__init__","type":null}},"_evaluate":{".class":"SymbolTableNode","kind":"Mdef","node":{".class":"FuncDef","abstract_status":0,"arg_kinds":[0,0],"arg_names":["self","row_index"],"dataclass_transform_spec":null,"deprecated":null,"flags":[],"fullname":"paddle.autograd.autograd._JacobianNoBatch._evaluate","name":"_evaluate","type":null}},"_flatten":{".class":"SymbolTableNode","kind":"Mdef","node":{".class":"FuncDef","abstract_status":0,"arg_kinds":[0,0],"arg_names":["self","xs"],"dataclass_transform_spec":null,"deprecated":null,"flags":[],"fullname":"paddle.autograd.autograd._JacobianNoBatch._flatten","name":"_flatten","type":null}},"_lazy_axis":{".class":"SymbolTableNode","kind":"Mdef","node":{".class":"Decorator","func":{".class":"FuncDef","abstract_status":0,"arg_kinds":[0],"arg_names":["self"],"dataclass_transform_spec":null,"deprecated":null,"flags":["is_property","is_decorated"],"fullname":"paddle.autograd.autograd._JacobianNoBatch._lazy_axis","name":"_lazy_axis","type":null},"is_overload":false,"var":{".class":"Var","flags":["is_initialized_in_class","is_property","is_ready","is_inferred"],"fullname":"paddle.autograd.autograd._JacobianNoBatch._lazy_axis","name":"_lazy_axis","type":{".class":"CallableType","arg_kinds":[0],"arg_names":["self"],"arg_types":["paddle.autograd.autograd._JacobianNoBatch"],"bound_args":[],"def_extras":{"first_arg":"self"},"fallback":"builtins.function","from_concatenate":false,"implicit":true,"imprecise_arg_kinds":false,"is_ellipsis_args":false,"name":"_lazy_axis of _JacobianNoBatch","ret_type":{".class":"AnyType","missing_import_name":null,"source_any":null,"type_of_any":1},"type_guard":null,"type_is":null,"unpack_kwargs":false,"variables":[]}}}},"inner_shape":{".class":"SymbolTableNode","implicit":true,"kind":"Mdef","node":{".class":"Var","flags":["is_inferred"],"fullname":"paddle.autograd.autograd._JacobianNoBatch.inner_shape","name":"inner_shape","type":{".class":"Instance","args":[{".class":"AnyType","missing_import_name":null,"source_any":{".class":"AnyType","missing_import_name":null,"source_any":null,"type_of_any":5},"type_of_any":7}],"extra_attrs":null,"type_ref":"builtins.list"}}},"is_batched":{".class":"SymbolTableNode","implicit":true,"kind":"Mdef","node":{".class":"Var","flags":["is_inferred"],"fullname":"paddle.autograd.autograd._JacobianNoBatch.is_batched","name":"is_batched","type":"builtins.bool"}},"shape":{".class":"SymbolTableNode","implicit":true,"kind":"Mdef","node":{".class":"Var","flags":["is_inferred"],"fullname":"paddle.autograd.autograd._JacobianNoBatch.shape","name":"shape","type":{".class":"Instance","args":[{".class":"AnyType","missing_import_name":null,"source_any":{".class":"AnyType","missing_import_name":null,"source_any":null,"type_of_any":5},"type_of_any":7}],"extra_attrs":null,"type_ref":"builtins.list"}}}},"self_type":{".class":"TypeVarType","default":{".class":"AnyType","missing_import_name":null,"source_any":null,"type_of_any":4},"fullname":"paddle.autograd.autograd._JacobianNoBatch.Self","id":0,"name":"Self","namespace":"","upper_bound":"paddle.autograd.autograd._JacobianNoBatch","values":[],"variance":0},"slots":null,"tuple_type":null,"type_vars":[],"typeddict_type":null}},"__annotations__":{".class":"SymbolTableNode","kind":"Gdef","node":{".class":"Var","flags":["is_ready"],"fullname":"paddle.autograd.autograd.__annotations__","name":"__annotations__","type":{".class":"Instance","args":["builtins.str",{".class":"AnyType","missing_import_name":null,"source_any":null,"type_of_any":6}],"extra_attrs":null,"type_ref":"builtins.dict"}}},"__doc__":{".class":"SymbolTableNode","kind":"Gdef","node":{".class":"Var","flags":["is_ready"],"fullname":"paddle.autograd.autograd.__doc__","name":"__doc__","type":"builtins.str"}},"__file__":{".class":"SymbolTableNode","kind":"Gdef","node":{".class":"Var","flags":["is_ready"],"fullname":"paddle.autograd.autograd.__file__","name":"__file__","type":"builtins.str"}},"__name__":{".class":"SymbolTableNode","kind":"Gdef","node":{".class":"Var","flags":["is_ready"],"fullname":"paddle.autograd.autograd.__name__","name":"__name__","type":"builtins.str"}},"__package__":{".class":"SymbolTableNode","kind":"Gdef","node":{".class":"Var","flags":["is_ready"],"fullname":"paddle.autograd.autograd.__package__","name":"__package__","type":"builtins.str"}},"__spec__":{".class":"SymbolTableNode","kind":"Gdef","node":{".class":"Var","flags":["is_ready"],"fullname":"paddle.autograd.autograd.__spec__","name":"__spec__","type":"_frozen_importlib.ModuleSpec"}},"_grad_for_jacobian":{".class":"SymbolTableNode","kind":"Gdef","node":{".class":"FuncDef","abstract_status":0,"arg_kinds":[0,0,1],"arg_names":["ys","xs","v"],"dataclass_transform_spec":null,"deprecated":null,"flags":[],"fullname":"paddle.autograd.autograd._grad_for_jacobian","name":"_grad_for_jacobian","type":null}},"_multi_index":{".class":"SymbolTableNode","kind":"Gdef","node":{".class":"FuncDef","abstract_status":0,"arg_kinds":[0,0],"arg_names":["indexes","shape"],"dataclass_transform_spec":null,"deprecated":null,"flags":[],"fullname":"paddle.autograd.autograd._multi_index","name":"_multi_index","type":null}},"_replace_none_with_zero_tensor":{".class":"SymbolTableNode","kind":"Gdef","node":{".class":"FuncDef","abstract_status":0,"arg_kinds":[0,0],"arg_names":["xs","refs"],"dataclass_transform_spec":null,"deprecated":null,"flags":[],"fullname":"paddle.autograd.autograd._replace_none_with_zero_tensor","name":"_replace_none_with_zero_tensor","type":null}},"annotations":{".class":"SymbolTableNode","cross_ref":"__future__.annotations","kind":"Gdef","module_hidden":true,"module_public":false},"as_tensors":{".class":"SymbolTableNode","kind":"Gdef","node":{".class":"FuncDef","abstract_status":0,"arg_kinds":[0],"arg_names":["xs"],"dataclass_transform_spec":null,"deprecated":null,"flags":[],"fullname":"paddle.autograd.autograd.as_tensors","name":"as_tensors","type":null}},"framework":{".class":"SymbolTableNode","cross_ref":"paddle.base.framework","kind":"Gdef","module_hidden":true,"module_public":false},"hessian":{".class":"SymbolTableNode","kind":"Gdef","node":{".class":"OverloadedFuncDef","deprecated":null,"flags":[],"fullname":"paddle.autograd.autograd.hessian","impl":{".class":"FuncDef","abstract_status":0,"arg_kinds":[0,0,1],"arg_names":["ys","xs","batch_axis"],"dataclass_transform_spec":null,"deprecated":null,"flags":["is_overload"],"fullname":"paddle.autograd.autograd.hessian","name":"hessian","type":null},"items":[{".class":"Decorator","func":{".class":"FuncDef","abstract_status":0,"arg_kinds":[0,0,1],"arg_names":["ys","xs","batch_axis"],"dataclass_transform_spec":null,"deprecated":null,"flags":["is_overload","is_decorated"],"fullname":"paddle.autograd.autograd.hessian","name":"hessian","type":{".class":"CallableType","arg_kinds":[0,0,1],"arg_names":["ys","xs","batch_axis"],"arg_types":["paddle.tensor.tensor.Tensor","paddle.tensor.tensor.Tensor",{".class":"UnionType","items":["builtins.int",{".class":"NoneType"}],"uses_pep604_syntax":true}],"bound_args":[],"def_extras":{"first_arg":null},"fallback":"builtins.function","from_concatenate":false,"implicit":false,"imprecise_arg_kinds":false,"is_ellipsis_args":false,"name":"hessian","ret_type":"paddle.autograd.autograd.Hessian","type_guard":null,"type_is":null,"unpack_kwargs":false,"variables":[]}},"is_overload":true,"var":{".class":"Var","flags":["is_ready","is_inferred"],"fullname":"paddle.autograd.autograd.hessian","name":"hessian","type":{".class":"CallableType","arg_kinds":[0,0,1],"arg_names":["ys","xs","batch_axis"],"arg_types":["paddle.tensor.tensor.Tensor","paddle.tensor.tensor.Tensor",{".class":"UnionType","items":["builtins.int",{".class":"NoneType"}],"uses_pep604_syntax":true}],"bound_args":[],"def_extras":{"first_arg":null},"fallback":"builtins.function","from_concatenate":false,"implicit":false,"imprecise_arg_kinds":false,"is_ellipsis_args":false,"name":"hessian","ret_type":"paddle.autograd.autograd.Hessian","type_guard":null,"type_is":null,"unpack_kwargs":false,"variables":[]}}},{".class":"Decorator","func":{".class":"FuncDef","abstract_status":0,"arg_kinds":[0,0,1],"arg_names":["ys","xs","batch_axis"],"dataclass_transform_spec":null,"deprecated":null,"flags":["is_overload","is_decorated"],"fullname":"paddle.autograd.autograd.hessian","name":"hessian","type":{".class":"CallableType","arg_kinds":[0,0,1],"arg_names":["ys","xs","batch_axis"],"arg_types":["paddle.tensor.tensor.Tensor",{".class":"Instance","args":["paddle.tensor.tensor.Tensor"],"extra_attrs":null,"type_ref":"typing.Sequence"},{".class":"UnionType","items":["builtins.int",{".class":"NoneType"}],"uses_pep604_syntax":true}],"bound_args":[],"def_extras":{"first_arg":null},"fallback":"builtins.function","from_concatenate":false,"implicit":false,"imprecise_arg_kinds":false,"is_ellipsis_args":false,"name":"hessian","ret_type":{".class":"Instance","args":[{".class":"Instance","args":["paddle.autograd.autograd.Hessian"],"extra_attrs":null,"type_ref":"builtins.tuple"}],"extra_attrs":null,"type_ref":"builtins.tuple"},"type_guard":null,"type_is":null,"unpack_kwargs":false,"variables":[]}},"is_overload":true,"var":{".class":"Var","flags":["is_ready","is_inferred"],"fullname":"paddle.autograd.autograd.hessian","name":"hessian","type":{".class":"CallableType","arg_kinds":[0,0,1],"arg_names":["ys","xs","batch_axis"],"arg_types":["paddle.tensor.tensor.Tensor",{".class":"Instance","args":["paddle.tensor.tensor.Tensor"],"extra_attrs":null,"type_ref":"typing.Sequence"},{".class":"UnionType","items":["builtins.int",{".class":"NoneType"}],"uses_pep604_syntax":true}],"bound_args":[],"def_extras":{"first_arg":null},"fallback":"builtins.function","from_concatenate":false,"implicit":false,"imprecise_arg_kinds":false,"is_ellipsis_args":false,"name":"hessian","ret_type":{".class":"Instance","args":[{".class":"Instance","args":["paddle.autograd.autograd.Hessian"],"extra_attrs":null,"type_ref":"builtins.tuple"}],"extra_attrs":null,"type_ref":"builtins.tuple"},"type_guard":null,"type_is":null,"unpack_kwargs":false,"variables":[]}}}],"type":{".class":"Overloaded","items":[{".class":"CallableType","arg_kinds":[0,0,1],"arg_names":["ys","xs","batch_axis"],"arg_types":["paddle.tensor.tensor.Tensor","paddle.tensor.tensor.Tensor",{".class":"UnionType","items":["builtins.int",{".class":"NoneType"}],"uses_pep604_syntax":true}],"bound_args":[],"def_extras":{"first_arg":null},"fallback":"builtins.function","from_concatenate":false,"implicit":false,"imprecise_arg_kinds":false,"is_ellipsis_args":false,"name":"hessian","ret_type":"paddle.autograd.autograd.Hessian","type_guard":null,"type_is":null,"unpack_kwargs":false,"variables":[]},{".class":"CallableType","arg_kinds":[0,0,1],"arg_names":["ys","xs","batch_axis"],"arg_types":["paddle.tensor.tensor.Tensor",{".class":"Instance","args":["paddle.tensor.tensor.Tensor"],"extra_attrs":null,"type_ref":"typing.Sequence"},{".class":"UnionType","items":["builtins.int",{".class":"NoneType"}],"uses_pep604_syntax":true}],"bound_args":[],"def_extras":{"first_arg":null},"fallback":"builtins.function","from_concatenate":false,"implicit":false,"imprecise_arg_kinds":false,"is_ellipsis_args":false,"name":"hessian","ret_type":{".class":"Instance","args":[{".class":"Instance","args":["paddle.autograd.autograd.Hessian"],"extra_attrs":null,"type_ref":"builtins.tuple"}],"extra_attrs":null,"type_ref":"builtins.tuple"},"type_guard":null,"type_is":null,"unpack_kwargs":false,"variables":[]}]}}},"jacobian":{".class":"SymbolTableNode","kind":"Gdef","node":{".class":"OverloadedFuncDef","deprecated":null,"flags":[],"fullname":"paddle.autograd.autograd.jacobian","impl":{".class":"FuncDef","abstract_status":0,"arg_kinds":[0,0,1],"arg_names":["ys","xs","batch_axis"],"dataclass_transform_spec":null,"deprecated":null,"flags":["is_overload"],"fullname":"paddle.autograd.autograd.jacobian","name":"jacobian","type":null},"items":[{".class":"Decorator","func":{".class":"FuncDef","abstract_status":0,"arg_kinds":[0,0,1],"arg_names":["ys","xs","batch_axis"],"dataclass_transform_spec":null,"deprecated":null,"flags":["is_overload","is_decorated"],"fullname":"paddle.autograd.autograd.jacobian","name":"jacobian","type":{".class":"CallableType","arg_kinds":[0,0,1],"arg_names":["ys","xs","batch_axis"],"arg_types":["paddle.tensor.tensor.Tensor","paddle.tensor.tensor.Tensor",{".class":"UnionType","items":["builtins.int",{".class":"NoneType"}],"uses_pep604_syntax":true}],"bound_args":[],"def_extras":{"first_arg":null},"fallback":"builtins.function","from_concatenate":false,"implicit":false,"imprecise_arg_kinds":false,"is_ellipsis_args":false,"name":"jacobian","ret_type":"paddle.autograd.autograd.Jacobian","type_guard":null,"type_is":null,"unpack_kwargs":false,"variables":[]}},"is_overload":true,"var":{".class":"Var","flags":["is_ready","is_inferred"],"fullname":"paddle.autograd.autograd.jacobian","name":"jacobian","type":{".class":"CallableType","arg_kinds":[0,0,1],"arg_names":["ys","xs","batch_axis"],"arg_types":["paddle.tensor.tensor.Tensor","paddle.tensor.tensor.Tensor",{".class":"UnionType","items":["builtins.int",{".class":"NoneType"}],"uses_pep604_syntax":true}],"bound_args":[],"def_extras":{"first_arg":null},"fallback":"builtins.function","from_concatenate":false,"implicit":false,"imprecise_arg_kinds":false,"is_ellipsis_args":false,"name":"jacobian","ret_type":"paddle.autograd.autograd.Jacobian","type_guard":null,"type_is":null,"unpack_kwargs":false,"variables":[]}}},{".class":"Decorator","func":{".class":"FuncDef","abstract_status":0,"arg_kinds":[0,0,1],"arg_names":["ys","xs","batch_axis"],"dataclass_transform_spec":null,"deprecated":null,"flags":["is_overload","is_decorated"],"fullname":"paddle.autograd.autograd.jacobian","name":"jacobian","type":{".class":"CallableType","arg_kinds":[0,0,1],"arg_names":["ys","xs","batch_axis"],"arg_types":[{".class":"Instance","args":["paddle.tensor.tensor.Tensor"],"extra_attrs":null,"type_ref":"typing.Sequence"},{".class":"Instance","args":["paddle.tensor.tensor.Tensor"],"extra_attrs":null,"type_ref":"typing.Sequence"},{".class":"UnionType","items":["builtins.int",{".class":"NoneType"}],"uses_pep604_syntax":true}],"bound_args":[],"def_extras":{"first_arg":null},"fallback":"builtins.function","from_concatenate":false,"implicit":false,"imprecise_arg_kinds":false,"is_ellipsis_args":false,"name":"jacobian","ret_type":{".class":"Instance","args":[{".class":"Instance","args":["paddle.autograd.autograd.Jacobian"],"extra_attrs":null,"type_ref":"builtins.tuple"}],"extra_attrs":null,"type_ref":"builtins.tuple"},"type_guard":null,"type_is":null,"unpack_kwargs":false,"variables":[]}},"is_overload":true,"var":{".class":"Var","flags":["is_ready","is_inferred"],"fullname":"paddle.autograd.autograd.jacobian","name":"jacobian","type":{".class":"CallableType","arg_kinds":[0,0,1],"arg_names":["ys","xs","batch_axis"],"arg_types":[{".class":"Instance","args":["paddle.tensor.tensor.Tensor"],"extra_attrs":null,"type_ref":"typing.Sequence"},{".class":"Instance","args":["paddle.tensor.tensor.Tensor"],"extra_attrs":null,"type_ref":"typing.Sequence"},{".class":"UnionType","items":["builtins.int",{".class":"NoneType"}],"uses_pep604_syntax":true}],"bound_args":[],"def_extras":{"first_arg":null},"fallback":"builtins.function","from_concatenate":false,"implicit":false,"imprecise_arg_kinds":false,"is_ellipsis_args":false,"name":"jacobian","ret_type":{".class":"Instance","args":[{".class":"Instance","args":["paddle.autograd.autograd.Jacobian"],"extra_attrs":null,"type_ref":"builtins.tuple"}],"extra_attrs":null,"type_ref":"builtins.tuple"},"type_guard":null,"type_is":null,"unpack_kwargs":false,"variables":[]}}},{".class":"Decorator","func":{".class":"FuncDef","abstract_status":0,"arg_kinds":[0,0,1],"arg_names":["ys","xs","batch_axis"],"dataclass_transform_spec":null,"deprecated":null,"flags":["is_overload","is_decorated"],"fullname":"paddle.autograd.autograd.jacobian","name":"jacobian","type":{".class":"CallableType","arg_kinds":[0,0,1],"arg_names":["ys","xs","batch_axis"],"arg_types":["paddle.tensor.tensor.Tensor",{".class":"Instance","args":["paddle.tensor.tensor.Tensor"],"extra_attrs":null,"type_ref":"typing.Sequence"},{".class":"UnionType","items":["builtins.int",{".class":"NoneType"}],"uses_pep604_syntax":true}],"bound_args":[],"def_extras":{"first_arg":null},"fallback":"builtins.function","from_concatenate":false,"implicit":false,"imprecise_arg_kinds":false,"is_ellipsis_args":false,"name":"jacobian","ret_type":{".class":"Instance","args":["paddle.autograd.autograd.Jacobian"],"extra_attrs":null,"type_ref":"builtins.tuple"},"type_guard":null,"type_is":null,"unpack_kwargs":false,"variables":[]}},"is_overload":true,"var":{".class":"Var","flags":["is_ready","is_inferred"],"fullname":"paddle.autograd.autograd.jacobian","name":"jacobian","type":{".class":"CallableType","arg_kinds":[0,0,1],"arg_names":["ys","xs","batch_axis"],"arg_types":["paddle.tensor.tensor.Tensor",{".class":"Instance","args":["paddle.tensor.tensor.Tensor"],"extra_attrs":null,"type_ref":"typing.Sequence"},{".class":"UnionType","items":["builtins.int",{".class":"NoneType"}],"uses_pep604_syntax":true}],"bound_args":[],"def_extras":{"first_arg":null},"fallback":"builtins.function","from_concatenate":false,"implicit":false,"imprecise_arg_kinds":false,"is_ellipsis_args":false,"name":"jacobian","ret_type":{".class":"Instance","args":["paddle.autograd.autograd.Jacobian"],"extra_attrs":null,"type_ref":"builtins.tuple"},"type_guard":null,"type_is":null,"unpack_kwargs":false,"variables":[]}}},{".class":"Decorator","func":{".class":"FuncDef","abstract_status":0,"arg_kinds":[0,0,1],"arg_names":["ys","xs","batch_axis"],"dataclass_transform_spec":null,"deprecated":null,"flags":["is_overload","is_decorated"],"fullname":"paddle.autograd.autograd.jacobian","name":"jacobian","type":{".class":"CallableType","arg_kinds":[0,0,1],"arg_names":["ys","xs","batch_axis"],"arg_types":[{".class":"Instance","args":["paddle.tensor.tensor.Tensor"],"extra_attrs":null,"type_ref":"typing.Sequence"},"paddle.tensor.tensor.Tensor",{".class":"UnionType","items":["builtins.int",{".class":"NoneType"}],"uses_pep604_syntax":true}],"bound_args":[],"def_extras":{"first_arg":null},"fallback":"builtins.function","from_concatenate":false,"implicit":false,"imprecise_arg_kinds":false,"is_ellipsis_args":false,"name":"jacobian","ret_type":{".class":"Instance","args":["paddle.autograd.autograd.Jacobian"],"extra_attrs":null,"type_ref":"builtins.tuple"},"type_guard":null,"type_is":null,"unpack_kwargs":false,"variables":[]}},"is_overload":true,"var":{".class":"Var","flags":["is_ready","is_inferred"],"fullname":"paddle.autograd.autograd.jacobian","name":"jacobian","type":{".class":"CallableType","arg_kinds":[0,0,1],"arg_names":["ys","xs","batch_axis"],"arg_types":[{".class":"Instance","args":["paddle.tensor.tensor.Tensor"],"extra_attrs":null,"type_ref":"typing.Sequence"},"paddle.tensor.tensor.Tensor",{".class":"UnionType","items":["builtins.int",{".class":"NoneType"}],"uses_pep604_syntax":true}],"bound_args":[],"def_extras":{"first_arg":null},"fallback":"builtins.function","from_concatenate":false,"implicit":false,"imprecise_arg_kinds":false,"is_ellipsis_args":false,"name":"jacobian","ret_type":{".class":"Instance","args":["paddle.autograd.autograd.Jacobian"],"extra_attrs":null,"type_ref":"builtins.tuple"},"type_guard":null,"type_is":null,"unpack_kwargs":false,"variables":[]}}}],"type":{".class":"Overloaded","items":[{".class":"CallableType","arg_kinds":[0,0,1],"arg_names":["ys","xs","batch_axis"],"arg_types":["paddle.tensor.tensor.Tensor","paddle.tensor.tensor.Tensor",{".class":"UnionType","items":["builtins.int",{".class":"NoneType"}],"uses_pep604_syntax":true}],"bound_args":[],"def_extras":{"first_arg":null},"fallback":"builtins.function","from_concatenate":false,"implicit":false,"imprecise_arg_kinds":false,"is_ellipsis_args":false,"name":"jacobian","ret_type":"paddle.autograd.autograd.Jacobian","type_guard":null,"type_is":null,"unpack_kwargs":false,"variables":[]},{".class":"CallableType","arg_kinds":[0,0,1],"arg_names":["ys","xs","batch_axis"],"arg_types":[{".class":"Instance","args":["paddle.tensor.tensor.Tensor"],"extra_attrs":null,"type_ref":"typing.Sequence"},{".class":"Instance","args":["paddle.tensor.tensor.Tensor"],"extra_attrs":null,"type_ref":"typing.Sequence"},{".class":"UnionType","items":["builtins.int",{".class":"NoneType"}],"uses_pep604_syntax":true}],"bound_args":[],"def_extras":{"first_arg":null},"fallback":"builtins.function","from_concatenate":false,"implicit":false,"imprecise_arg_kinds":false,"is_ellipsis_args":false,"name":"jacobian","ret_type":{".class":"Instance","args":[{".class":"Instance","args":["paddle.autograd.autograd.Jacobian"],"extra_attrs":null,"type_ref":"builtins.tuple"}],"extra_attrs":null,"type_ref":"builtins.tuple"},"type_guard":null,"type_is":null,"unpack_kwargs":false,"variables":[]},{".class":"CallableType","arg_kinds":[0,0,1],"arg_names":["ys","xs","batch_axis"],"arg_types":["paddle.tensor.tensor.Tensor",{".class":"Instance","args":["paddle.tensor.tensor.Tensor"],"extra_attrs":null,"type_ref":"typing.Sequence"},{".class":"UnionType","items":["builtins.int",{".class":"NoneType"}],"uses_pep604_syntax":true}],"bound_args":[],"def_extras":{"first_arg":null},"fallback":"builtins.function","from_concatenate":false,"implicit":false,"imprecise_arg_kinds":false,"is_ellipsis_args":false,"name":"jacobian","ret_type":{".class":"Instance","args":["paddle.autograd.autograd.Jacobian"],"extra_attrs":null,"type_ref":"builtins.tuple"},"type_guard":null,"type_is":null,"unpack_kwargs":false,"variables":[]},{".class":"CallableType","arg_kinds":[0,0,1],"arg_names":["ys","xs","batch_axis"],"arg_types":[{".class":"Instance","args":["paddle.tensor.tensor.Tensor"],"extra_attrs":null,"type_ref":"typing.Sequence"},"paddle.tensor.tensor.Tensor",{".class":"UnionType","items":["builtins.int",{".class":"NoneType"}],"uses_pep604_syntax":true}],"bound_args":[],"def_extras":{"first_arg":null},"fallback":"builtins.function","from_concatenate":false,"implicit":false,"imprecise_arg_kinds":false,"is_ellipsis_args":false,"name":"jacobian","ret_type":{".class":"Instance","args":["paddle.autograd.autograd.Jacobian"],"extra_attrs":null,"type_ref":"builtins.tuple"},"type_guard":null,"type_is":null,"unpack_kwargs":false,"variables":[]}]}}},"overload":{".class":"SymbolTableNode","cross_ref":"typing.overload","kind":"Gdef","module_hidden":true,"module_public":false},"paddle":{".class":"SymbolTableNode","cross_ref":"paddle","kind":"Gdef","module_hidden":true,"module_public":false}},"path":"/Library/Frameworks/Python.framework/Versions/3.12/lib/python3.12/site-packages/paddle/autograd/autograd.py"}